stignore_agent/__init__.py
stignore_agent/app.py
stignore_agent/helpers.py
stignore_agent-0.0.15.data/scripts/stignore-agent
stignore_agent-0.0.15.dist-info/LICENSE
stignore_agent-0.0.15.dist-info/METADATA
stignore_agent-0.0.15.dist-info/WHEEL
stignore_agent-0.0.15.dist-info/top_level.txt
stignore_agent-0.0.15.dist-info/RECORD
